MANIFEST.in
README.rst
colorunit.py
setup.cfg
setup.py
nose_colorxunit.egg-info/PKG-INFO
nose_colorxunit.egg-info/SOURCES.txt
nose_colorxunit.egg-info/dependency_links.txt
nose_colorxunit.egg-info/entry_points.txt
nose_colorxunit.egg-info/not-zip-safe
nose_colorxunit.egg-info/requires.txt
nose_colorxunit.egg-info/top_level.txt