Metadata-Version: 1.1
Name: nose-colorxunit
Version: 0.1.5
Summary: make unittest formatted and colorful output(cross platform)
Home-page: https://github.com/walkingnine/colorunit
Author: Lesus
Author-email: walkingnine@gmail.com
License: Apache License,Version 2.0
Keywords: nose nosetest xunit
Platform: UNKNOWN
Classifier: Development Status :: 3 - Alpha
Classifier: License :: OSI Approved :: Apache Software License
Classifier: Operating System :: OS Independent
Classifier: Programming Language :: Python
Classifier: Programming Language :: Python :: 2.7
Classifier: Programming Language :: Python :: Implementation :: CPython
Classifier: Topic :: Software Development :: Testing
